{
  "placeholderImages": [
    {
      "id": "sara-profile",
      "description": "Portrait of Sara Gavilán, junior web developer, React and SQL.",
      "imageUrl": "/img/sara-profile.jpg",
      "imageHint": "woman portrait"
    },
    {
      "id": "natura-puzzle",
      "description": "Natura Puzzle project screenshot",
      "imageUrl": "/img/natura-puzzle.png",
      "imageHint": "puzzle game"
    },
    {
      "id": "poke-finder",
      "description": "Poke Finder project screenshot",
      "imageUrl": "/img/poke-finder.png",
      "imageHint": "search app"
    },
    {
      "id": "mockup-react-native",
      "description": "Mockup de la app React Native Vume",
      "imageUrl": "/img/mockup-react-native.png",
      "imageHint": "mobile app mockup"
    }
  ]
}
